{
  "origin_date": "2026-05-05",
  "target_date": "2026-05-06",
  "point_yoy_pct": 1.87546,
  "selected_point_model": "persistence",
  "raw_point_pre_correction_pct": 1.87546,
  "ridge_raw_point_pct": 1.8896691377415342,
  "bias_correction_pp": 0.0,
  "today_published_yoy": 1.87546,
  "delta_vs_today_pp": 0.0,
  "band_80": [
    1.818031,
    1.9612139999999998
  ],
  "band_95": [
    1.6463569999999998,
    2.092797
  ],
  "band_80_width_pp": 0.14318299999999984,
  "band_95_width_pp": 0.44644000000000017,
  "ridge_alpha": 0.1,
  "intercept": 0.3328984074950596,
  "lag_coef": 0.9966511708186534,
  "n_train": 1555,
  "n_calib": 30,
  "backtest": {
    "n_origins": 90,
    "window_start": "2026-02-04",
    "window_end": "2026-05-04",
    "rmse_model": 0.1400909225335321,
    "rmse_naive": 0.1259461674451077,
    "rmse_reduction_pct": -11.2307943745801,
    "mae_model": 0.08659421032075916,
    "coverage_80": 0.7555555555555555,
    "coverage_95": 0.9222222222222223,
    "directional_accuracy": 0.6333333333333333,
    "base_rate_up": 0.6222222222222222,
    "ship_verdict": "BASELINE"
  },
  "drivers": []
}